PyDataCore/__init__.py
PyDataCore/data.py
PyDataCore/datapool.py
PyDataCore-1.1.2.dist-info/LICENSE
PyDataCore-1.1.2.dist-info/METADATA
PyDataCore-1.1.2.dist-info/WHEEL
PyDataCore-1.1.2.dist-info/top_level.txt
PyDataCore-1.1.2.dist-info/RECORD
