Metadata-Version: 2.1
Name: PyDataCore
Version: 1.1.2
Summary: A data library for handling temporal, frequency signals, and data pools.
Home-page: https://github.com/GuillaumeTrain/PyDataCore
Author: Guillaume Train
Author-email: g.train@live.fr
Classifier: Programming Language :: Python :: 3
Classifier: License :: OSI Approved :: MIT License
Classifier: Operating System :: OS Independent
Requires-Python: >=3.10
License-File: LICENSE
Requires-Dist: numpy ~=2.1.2
Requires-Dist: termcolor ~=2.5.0
Requires-Dist: pandas ~=2.2.3
Requires-Dist: setuptools ~=75.2.0
Requires-Dist: pytz ~=2024.2
Requires-Dist: six ~=1.16.0
Requires-Dist: tzdata ~=2024.2
Requires-Dist: python-dateutil ~=2.9.0.post0
Requires-Dist: tabulate ~=0.9.0
